{"web":{"client_id":"786924916548-ejgbsv83h2boi331394o2pvns7sngf90.apps.googleusercontent.com","project_id":"item-catalog-app-175623","auth_uri":"https://accounts.google.com/o/oauth2/auth","token_uri":"https://accounts.google.com/o/oauth2/token","auth_provider_x509_cert_url":"https://www.googleapis.com/oauth2/v1/certs","client_secret":"Bfh31aLPmt8dO5GNWdf-l56R","redirect_uris":["http://ec2-54-156-227-190.compute-1.amazonaws.com","http://localhost:8000","http://localhost:8000/login","http://localhost:8000/gconnect","http://ec2-54-156-227-190.compute-1.amazonaws.com:8000/login","http://ec2-54-156-227-190.compute-1.amazonaws.com:8000","http://ec2-54-156-227-190.compute-1.amazonaws.com:8000/gconnect","http://ec2-54-156-227-190.compute-1.amazonaws.com:80/login","http://ec2-54-156-227-190.compute-1.amazonaws.com:80/gconnect","http://54.156.227.190.xip.io:80","http://54.156.227.190.xip.io:8000","http://54.156.227.190.xip.io:8000/login","http://54.156.227.190.xip.io:80/login","http://54.156.227.190.xip.io:80/gconnect","http://54.156.227.190.xip.io:8000/gconnect"],"javascript_origins":["http://ec2-54-156-227-190.compute-1.amazonaws.com","http://ec2-54-156-227-190.compute-1.amazonaws.com:8000","http://54.156.227.190.xip.io","http://54.156.227.190.xip.io:8000","http://54.156.227.190.xip.io:80"]}}